{"1":{"ID":1,"Type":2,"Value":44,"GuideID":0,"Corner":["Feature","Plant"],"AppearPiece":[],"AppearMap":"","UnlockArea":""},"2":{"ID":2,"Type":1,"Value":1,"GuideID":0,"Corner":[],"AppearPiece":[],"AppearMap":"","UnlockArea":""},"3":{"ID":3,"Type":1,"Value":1,"GuideID":0,"Corner":["Feature","Breed"],"AppearPiece":[],"AppearMap":"","UnlockArea":""},"4":{"ID":4,"Type":2,"Value":63,"GuideID":0,"Corner":["Feature","Food"],"AppearPiece":[],"AppearMap":"","UnlockArea":""},"5":{"ID":5,"Type":2,"Value":11,"GuideID":0,"Corner":[],"AppearPiece":[],"AppearMap":"","UnlockArea":""},"6":{"ID":6,"Type":1,"Value":1,"GuideID":0,"Corner":["Feature","Make"],"AppearPiece":[],"AppearMap":"","UnlockArea":""},"7":{"ID":7,"Type":1,"Value":1,"GuideID":0,"Corner":[],"AppearPiece":[],"AppearMap":"","UnlockArea":""},"8":{"ID":8,"Type":1,"Value":1,"GuideID":0,"Corner":["Feature","Delivery"],"AppearPiece":[],"AppearMap":"","UnlockArea":""},"9":{"ID":9,"Type":1,"Value":1,"GuideID":0,"Corner":[],"AppearPiece":[],"AppearMap":"","UnlockArea":""},"10":{"ID":10,"Type":2,"Value":23,"GuideID":0,"Corner":[],"AppearPiece":[],"AppearMap":"","UnlockArea":""},"11":{"ID":11,"Type":1,"Value":1,"GuideID":0,"Corner":[],"AppearPiece":[],"AppearMap":"","UnlockArea":""},"12":{"ID":12,"Type":1,"Value":1,"GuideID":0,"Corner":[],"AppearPiece":[],"AppearMap":"","UnlockArea":""},"13":{"ID":13,"Type":1,"Value":1,"GuideID":0,"Corner":[],"AppearPiece":[],"AppearMap":"","UnlockArea":""},"14":{"ID":14,"Type":1,"Value":1,"GuideID":0,"Corner":[],"AppearPiece":[],"AppearMap":"","UnlockArea":""},"15":{"ID":15,"Type":1,"Value":18,"GuideID":0,"Corner":[],"AppearPiece":[],"AppearMap":"","UnlockArea":""},"16":{"ID":16,"Type":1,"Value":18,"GuideID":0,"Corner":[],"AppearPiece":[],"AppearMap":"","UnlockArea":""},"17":{"ID":17,"Type":1,"Value":18,"GuideID":0,"Corner":[],"AppearPiece":[],"AppearMap":"","UnlockArea":""},"18":{"ID":18,"Type":1,"Value":7,"GuideID":0,"Corner":[],"AppearPiece":[],"AppearMap":"","UnlockArea":""},"19":{"ID":19,"Type":1,"Value":5,"GuideID":0,"Corner":[],"AppearPiece":[],"AppearMap":"","UnlockArea":""},"20":{"ID":20,"Type":1,"Value":18,"GuideID":0,"Corner":[],"AppearPiece":[],"AppearMap":"","UnlockArea":""},"21":{"ID":21,"Type":1,"Value":18,"GuideID":0,"Corner":[],"AppearPiece":[],"AppearMap":"","UnlockArea":""},"22":{"ID":22,"Type":1,"Value":18,"GuideID":0,"Corner":[],"AppearPiece":[],"AppearMap":"","UnlockArea":""},"23":{"ID":23,"Type":1,"Value":6,"GuideID":0,"Corner":[],"AppearPiece":[],"AppearMap":"","UnlockArea":""},"24":{"ID":24,"Type":1,"Value":4,"GuideID":0,"Corner":[],"AppearPiece":[],"AppearMap":"","UnlockArea":""},"200":{"ID":200,"Type":1,"Value":16,"GuideID":0,"Corner":[],"AppearPiece":[],"AppearMap":"","UnlockArea":""},"201":{"ID":201,"Type":1,"Value":17,"GuideID":0,"Corner":[],"AppearPiece":[],"AppearMap":"","UnlockArea":""},"202":{"ID":202,"Type":1,"Value":18,"GuideID":0,"Corner":[],"AppearPiece":[],"AppearMap":"","UnlockArea":""},"203":{"ID":203,"Type":1,"Value":18,"GuideID":0,"Corner":[],"AppearPiece":[],"AppearMap":"","UnlockArea":""},"204":{"ID":204,"Type":1,"Value":18,"GuideID":0,"Corner":[],"AppearPiece":[],"AppearMap":"","UnlockArea":""},"300":{"ID":300,"Type":3,"Value":0,"GuideID":0,"Corner":[],"AppearPiece":[],"AppearMap":"","UnlockArea":""},"301":{"ID":301,"Type":1,"Value":1,"GuideID":0,"Corner":[],"AppearPiece":[],"AppearMap":"","UnlockArea":""},"302":{"ID":302,"Type":1,"Value":5,"GuideID":0,"Corner":[],"AppearPiece":[],"AppearMap":"","UnlockArea":""},"303":{"ID":303,"Type":1,"Value":7,"GuideID":0,"Corner":["Feature","Mailbox"],"AppearPiece":[],"AppearMap":"","UnlockArea":""},"401":{"ID":401,"Type":2,"Value":12,"GuideID":0,"Corner":[],"AppearPiece":[],"AppearMap":"","UnlockArea":"2~-6~-2~6~6~2"},"402":{"ID":402,"Type":2,"Value":25,"GuideID":0,"Corner":[],"AppearPiece":[],"AppearMap":"","UnlockArea":"2~-6~2~6~6~6"},"403":{"ID":403,"Type":2,"Value":54,"GuideID":0,"Corner":[],"AppearPiece":[],"AppearMap":"","UnlockArea":"-2~-6~2~2~6~6"},"432":{"ID":432,"Type":2,"Value":19,"GuideID":0,"Corner":[],"AppearPiece":[[1,100],[601,1]],"AppearMap":"12_2_0","UnlockArea":""},"433":{"ID":433,"Type":2,"Value":29,"GuideID":0,"Corner":[],"AppearPiece":[[1,100],[604,1]],"AppearMap":"12_3_0","UnlockArea":""},"434":{"ID":434,"Type":2,"Value":59,"GuideID":0,"Corner":[],"AppearPiece":[[1,100]],"AppearMap":"12_4_0","UnlockArea":""},"461":{"ID":461,"Type":2,"Value":80,"GuideID":0,"Corner":[],"AppearPiece":[[602,1]],"AppearMap":"12_4_2","UnlockArea":""},"462":{"ID":462,"Type":2,"Value":104,"GuideID":0,"Corner":[],"AppearPiece":[[605,1]],"AppearMap":"12_4_3","UnlockArea":""},"501":{"ID":501,"Type":2,"Value":33,"GuideID":0,"Corner":[],"AppearPiece":[],"AppearMap":"","UnlockArea":""},"502":{"ID":502,"Type":2,"Value":84,"GuideID":0,"Corner":[],"AppearPiece":[],"AppearMap":"","UnlockArea":""},"503":{"ID":503,"Type":1,"Value":1,"GuideID":0,"Corner":[],"AppearPiece":[],"AppearMap":"","UnlockArea":""}}